django_hell_auth/__init__.py
django_hell_auth/oidc.py
django_hell_auth/settings.py
django_hell_auth/urls.py
django_hell_auth/views.py
django_hell_auth-0.0.3.dist-info/LICENSE
django_hell_auth-0.0.3.dist-info/WHEEL
django_hell_auth-0.0.3.dist-info/METADATA
django_hell_auth-0.0.3.dist-info/RECORD
