Metadata-Version: 2.1
Name: django-hell-auth
Version: 0.0.3
Summary: hell gitlab auth for django
License: MIT
Author: David Bauer
Author-email: hausprojekt@debauer.de
Requires-Python: >=3.10,<4.0
Classifier: License :: OSI Approved :: MIT License
Classifier: Programming Language :: Python :: 3
Classifier: Programming Language :: Python :: 3.10
Classifier: Programming Language :: Python :: 3.11
Requires-Dist: Django (>=4.0.5,<5.0.0)
Requires-Dist: pre-commit (>=3.2.2,<4.0.0)
Requires-Dist: requests (>=2.28.2,<3.0.0)
Requires-Dist: types-requests (>=2.28.11.17,<3.0.0.0)
